{
  "_format": "hh-sol-cache-2",
  "files": {
    "/Users/olivierwinkler/dev/blockchain/my-wave-portal/contracts/WavePortal.sol": {
      "lastModificationDate": 1637174331579,
      "contentHash": "0a232047ab491d408cb392b5537c1e4b",
      "sourceName": "contracts/WavePortal.sol",
      "solcConfig": {
        "version": "0.8.4",
        "settings": {
          "optimizer": {
            "enabled": false,
            "runs": 200
          },
          "outputSelection": {
            "*": {
              "*": [
                "abi",
                "evm.bytecode",
                "evm.deployedBytecode",
                "evm.methodIdentifiers",
                "metadata"
              ],
              "": [
                "ast"
              ]
            }
          }
        }
      },
      "imports": [
        "@chainlink/contracts/src/v0.8/VRFConsumerBase.sol",
        "hardhat/console.sol"
      ],
      "versionPragmas": [
        "^0.8.4"
      ],
      "artifacts": [
        "WavePortal"
      ]
    },
    "/Users/olivierwinkler/dev/blockchain/my-wave-portal/node_modules/hardhat/console.sol": {
      "lastModificationDate": 1636827453592,
      "contentHash": "cc4777addd464ea56fa35b1c45df0591",
      "sourceName": "hardhat/console.sol",
      "solcConfig": {
        "version": "0.8.4",
        "settings": {
          "optimizer": {
            "enabled": false,
            "runs": 200
          },
          "outputSelection": {
            "*": {
              "*": [
                "abi",
                "evm.bytecode",
                "evm.deployedBytecode",
                "evm.methodIdentifiers",
                "metadata"
              ],
              "": [
                "ast"
              ]
            }
          }
        }
      },
      "imports": [],
      "versionPragmas": [
        ">=0.4.22 <0.9.0"
      ],
      "artifacts": [
        "console"
      ]
    },
    "/Users/olivierwinkler/dev/blockchain/my-wave-portal/node_modules/@chainlink/contracts/src/v0.8/VRFConsumerBase.sol": {
      "lastModificationDate": 1637004293271,
      "contentHash": "b2cd4396ec9f9d0b2dd385cc26d54298",
      "sourceName": "@chainlink/contracts/src/v0.8/VRFConsumerBase.sol",
      "solcConfig": {
        "version": "0.8.4",
        "settings": {
          "optimizer": {
            "enabled": false,
            "runs": 200
          },
          "outputSelection": {
            "*": {
              "*": [
                "abi",
                "evm.bytecode",
                "evm.deployedBytecode",
                "evm.methodIdentifiers",
                "metadata"
              ],
              "": [
                "ast"
              ]
            }
          }
        }
      },
      "imports": [
        "./interfaces/LinkTokenInterface.sol",
        "./VRFRequestIDBase.sol"
      ],
      "versionPragmas": [
        "^0.8.0"
      ],
      "artifacts": [
        "VRFConsumerBase"
      ]
    },
    "/Users/olivierwinkler/dev/blockchain/my-wave-portal/node_modules/@chainlink/contracts/src/v0.8/interfaces/LinkTokenInterface.sol": {
      "lastModificationDate": 1637004293287,
      "contentHash": "6d810dc28dac1e67147711dd3b35aae2",
      "sourceName": "@chainlink/contracts/src/v0.8/interfaces/LinkTokenInterface.sol",
      "solcConfig": {
        "version": "0.8.4",
        "settings": {
          "optimizer": {
            "enabled": false,
            "runs": 200
          },
          "outputSelection": {
            "*": {
              "*": [
                "abi",
                "evm.bytecode",
                "evm.deployedBytecode",
                "evm.methodIdentifiers",
                "metadata"
              ],
              "": [
                "ast"
              ]
            }
          }
        }
      },
      "imports": [],
      "versionPragmas": [
        "^0.8.0"
      ],
      "artifacts": [
        "LinkTokenInterface"
      ]
    },
    "/Users/olivierwinkler/dev/blockchain/my-wave-portal/node_modules/@chainlink/contracts/src/v0.8/VRFRequestIDBase.sol": {
      "lastModificationDate": 1637004293272,
      "contentHash": "cd3cfe02e0dcd3100ba2fef4ee94bb9e",
      "sourceName": "@chainlink/contracts/src/v0.8/VRFRequestIDBase.sol",
      "solcConfig": {
        "version": "0.8.4",
        "settings": {
          "optimizer": {
            "enabled": false,
            "runs": 200
          },
          "outputSelection": {
            "*": {
              "*": [
                "abi",
                "evm.bytecode",
                "evm.deployedBytecode",
                "evm.methodIdentifiers",
                "metadata"
              ],
              "": [
                "ast"
              ]
            }
          }
        }
      },
      "imports": [],
      "versionPragmas": [
        "^0.8.0"
      ],
      "artifacts": [
        "VRFRequestIDBase"
      ]
    }
  }
}
